hostxray/__init__.py
hostxray/api.py
hostxray/cli.py
hostxray/collect.py
hostxray/model.py
hostxray/redaction.py
hostxray/collectors/__init__.py
hostxray/collectors/core.py
hostxray/collectors/windows.py
hostxray/exporters/__init__.py
hostxray/exporters/json.py
hostxray/utils/__init__.py
hostxray/utils/exec.py
hostxray/utils/net.py
hostxray/utils/platform.py
hostxray/utils/timing.py
hostxray-0.0.0.dist-info/licenses/LICENSE
hostxray-0.0.0.dist-info/METADATA
hostxray-0.0.0.dist-info/WHEEL
hostxray-0.0.0.dist-info/entry_points.txt
hostxray-0.0.0.dist-info/top_level.txt
hostxray-0.0.0.dist-info/RECORD
