Metadata-Version: 2.4
Name: hostxray
Version: 0.0.0
Summary: Best-effort host specification capture for environment comparison, troubleshooting, and LLM context.
Author-email: Brent Carpenetti <brentwc.git@pm.me>
License: MIT License
Requires-Python: >=3.12
License-File: LICENSE
Provides-Extra: full
Requires-Dist: psutil; extra == "full"
Requires-Dist: pywin32; platform_system == "Windows" and extra == "full"
Provides-Extra: test
Requires-Dist: pytest>=7.0.0; extra == "test"
Requires-Dist: pytest-cov>=4.0.0; extra == "test"
Provides-Extra: dev
Requires-Dist: pytest>=7.0.0; extra == "dev"
Requires-Dist: pytest-cov>=4.0.0; extra == "dev"
Requires-Dist: black; extra == "dev"
Requires-Dist: flake8; extra == "dev"
Requires-Dist: mypy; extra == "dev"
Requires-Dist: isort; extra == "dev"
Provides-Extra: all
Requires-Dist: psutil; extra == "all"
Requires-Dist: pywin32; platform_system == "Windows" and extra == "all"
Requires-Dist: pytest>=7.0.0; extra == "all"
Requires-Dist: pytest-cov>=4.0.0; extra == "all"
Requires-Dist: black; extra == "all"
Requires-Dist: flake8; extra == "all"
Requires-Dist: mypy; extra == "all"
Requires-Dist: isort; extra == "all"
Dynamic: license-file
